pyObjective/__init__.py
pyObjective-0.1.4.dist-info/LICENSE
pyObjective-0.1.4.dist-info/METADATA
pyObjective-0.1.4.dist-info/WHEEL
pyObjective-0.1.4.dist-info/top_level.txt
pyObjective-0.1.4.dist-info/RECORD
