Metadata-Version: 2.1
Name: pyObjective
Version: 0.1.4
Summary: A tool to allow optimization of complex objects using scipy.optimize
Home-page: https://github.com/dev10110/pyObjective
Author: Devansh Agrawal
Author-email: devanshinspace@gmail.com
License: UNKNOWN
Platform: UNKNOWN
Classifier: Programming Language :: Python :: 3
Classifier: License :: OSI Approved :: MIT License
Classifier: Operating System :: OS Independent
Requires-Dist: scipy
Requires-Dist: prettytable
